gpcsd/__init__.py
gpcsd/covariances.py
gpcsd/forward_models.py
gpcsd/gpcsd1d.py
gpcsd/gpcsd2d.py
gpcsd/predict_csd.py
gpcsd/priors.py
gpcsd/utility_functions.py
gpcsd-1.0.2.dist-info/LICENSE
gpcsd-1.0.2.dist-info/METADATA
gpcsd-1.0.2.dist-info/WHEEL
gpcsd-1.0.2.dist-info/top_level.txt
gpcsd-1.0.2.dist-info/RECORD
