Metadata-Version: 2.1
Name: gpcsd
Version: 1.0.2
Summary: Gaussian process current source density estimation
Home-page: https://github.com/natalieklein/gpcsd
Author: Natalie Klein
Author-email: natalie.elizabeth.klein@gmail.com
License: UNKNOWN
Project-URL: Paper, https://arxiv.org/abs/2104.10070
Platform: UNKNOWN
Classifier: Development Status :: 4 - Beta
Classifier: Intended Audience :: Science/Research
Classifier: Topic :: Scientific/Engineering
Classifier: License :: OSI Approved :: MIT License
Classifier: Programming Language :: Python :: 3.7
Classifier: Programming Language :: Python :: 3.8
Classifier: Programming Language :: Python :: 3.9
Requires-Python: >=3.7, <4
License-File: LICENSE
Requires-Dist: autograd
Requires-Dist: h5py (>=3.2.1)
Requires-Dist: matplotlib
Requires-Dist: networkx (>=2.6.2)
Requires-Dist: numpy (>=1.20.3)
Requires-Dist: scikit-image (>=0.18.1)
Requires-Dist: scipy (>=1.6.2)
Requires-Dist: tqdm
Requires-Dist: joblib
